acmems/__init__.py
acme_mgmtserver-0.5.0.dist-info/WHEEL
acme_mgmtserver-0.5.0.dist-info/entry_points.txt
acme_mgmtserver-0.5.0.dist-info/METADATA
acme_mgmtserver-0.5.0.dist-info/RECORD
