Metadata-Version: 2.4
Name: acme-mgmtserver
Version: 0.5.0
Summary: Deprecated: software has been renamed to 'macen'
Keywords: acme,server,client,proxy,letsencrypt
Author: Malte Swart
Author-email: Malte Swart <mswart@devtation.de>
License-Expression: GPL-3.0-or-later
Classifier: Development Status :: 7 - Inactive
Classifier: Intended Audience :: System Administrators
Classifier: Topic :: Internet :: WWW/HTTP :: HTTP Servers
Classifier: Topic :: Security :: Cryptography
Classifier: Topic :: System :: Networking
Classifier: Topic :: System :: Systems Administration
Classifier: Topic :: Utilities
Classifier: License :: OSI Approved :: GNU General Public License v3 (GPLv3)
Classifier: Programming Language :: Python :: 3 :: Only
Classifier: Programming Language :: Python :: 3
Classifier: Programming Language :: Python :: 3.10
Classifier: Programming Language :: Python :: 3.11
Classifier: Programming Language :: Python :: 3.12
Classifier: Programming Language :: Python :: 3.13
Requires-Dist: macen==0.5.0
Requires-Python: >=3.10
Project-URL: Changelog, https://github.com/mswart/macen/blob/master/CHANGELOG.rst
Project-URL: Issues, https://github.com/mswart/macen/issues
Project-URL: Repository, https://github.com/mswart/macen
